CHANGES.txt
MANIFEST.in
README.rst
buildout.cfg
setup.py
speedtest.py
spraytest.py
netaccess_perfmetrics.egg-info/PKG-INFO
netaccess_perfmetrics.egg-info/SOURCES.txt
netaccess_perfmetrics.egg-info/dependency_links.txt
netaccess_perfmetrics.egg-info/entry_points.txt
netaccess_perfmetrics.egg-info/not-zip-safe
netaccess_perfmetrics.egg-info/requires.txt
netaccess_perfmetrics.egg-info/top_level.txt
perfmetrics/__init__.py
perfmetrics/clientstack.py
perfmetrics/statsd.py
perfmetrics/tests/__init__.py
perfmetrics/tests/test_clientstack.py
perfmetrics/tests/test_perfmetrics.py
perfmetrics/tests/test_statsd.py