Metadata-Version: 1.1
Name: netaccess-perfmetrics
Version: 2.3
Summary: Send performance metrics about Python code to Statsd
Home-page: https://github.com/NetAccessCorp/perfmetrics
Author: Shane Hathaway
Author-email: shane@hathawaymix.org
License: BSD-derived (http://www.repoze.org/LICENSE.txt)
Platform: UNKNOWN
Classifier: Development Status :: 5 - Production/Stable
Classifier: Intended Audience :: Developers
Classifier: Programming Language :: Python :: 2
Classifier: Programming Language :: Python :: 3
Classifier: License :: Repoze Public License
Classifier: Topic :: System :: Monitoring
